ap_cfg/__init__.py
ap_cfg/__version__.py
ap_cfg/app.py
ap_cfg/doc.py
ap_cfg/parms.py
ap_cfg/py.typed
ap_cfg/setup.py
ap_cfg/task.py
ap_cfg/cfg/log.std.yml
ap_cfg/cfg/log.usr.yml
ap_cfg-2.0.0.20251021.dist-info/licenses/LICENSE.txt
ap_cfg-2.0.0.20251021.dist-info/METADATA
ap_cfg-2.0.0.20251021.dist-info/WHEEL
ap_cfg-2.0.0.20251021.dist-info/entry_points.txt
ap_cfg-2.0.0.20251021.dist-info/top_level.txt
ap_cfg-2.0.0.20251021.dist-info/RECORD
